{"nm":"Untitled file","ddd":0,"h":2800,"w":1200,"meta":{"g":"@lottiefiles/creator 1.12.0"},"layers":[{"ty":4,"nm":"eye-center-2","sr":1,"st":0,"op":129.98,"ip":0,"hd":false,"ddd":0,"bm":0,"hasMask":false,"ao":0,"ks":{"a":{"a":0,"k":[85.0270004272461,85.0250015258789]},"s":{"a":0,"k":[29,29]},"sk":{"a":0,"k":0},"p":{"a":1,"k":[{"o":{"x":0.167,"y":0.167},"i":{"x":0.833,"y":0.833},"s":[638.9643,1401.5193],"t":0},{"o":{"x":0.167,"y":0.167},"i":{"x":0.833,"y":0.833},"s":[638.9643,1401.5193],"t":18},{"s":[1406.9643,1401.5193],"t":78}]},"r":{"a":1,"k":[{"o":{"x":0.167,"y":0.167},"i":{"x":0.833,"y":0.833},"s":[0],"t":0},{"o":{"x":0.167,"y":0.167},"i":{"x":0.833,"y":0.833},"s":[0],"t":18},{"s":[1080],"t":78}]},"sa":{"a":0,"k":0},"o":{"a":0,"k":100}},"shapes":[{"ty":"gr","bm":0,"hd":false,"nm":"Group 1","it":[{"ty":"sh","bm":0,"hd":false,"nm":"Path 1","d":1,"ks":{"a":0,"k":{"c":true,"i":[[0,0],[0,0],[24.069000000000003,0],[10.866399999999999,8.433000000000021],[0,0],[-12.1314,7.8703]],"o":[[0,0],[-10.975999999999999,19.561999999999983],[-14.83319999999999,0],[0,0],[4.6031999999999975,-13.9758],[0,0]],"v":[[50.0762,32.3086],[141.024,117.215],[85.005,150],[45.648,136.545],[24.0439,66.006],[50.0762,32.3086]]}}},{"ty":"st","bm":0,"hd":false,"nm":"Stroke","lc":1,"lj":1,"ml":4,"o":{"a":0,"k":100},"w":{"a":0,"k":1},"c":{"a":0,"k":[0.9804,0.9882,0.9961]}},{"ty":"fl","bm":0,"hd":false,"nm":"Fill","c":{"a":0,"k":[0.9804,0.9882,0.9961]},"r":1,"o":{"a":0,"k":100}},{"ty":"tr","a":{"a":0,"k":[82.53395080566406,91.15430068969727]},"s":{"a":0,"k":[100,100]},"sk":{"a":0,"k":0},"p":{"a":0,"k":[82.53395080566406,91.15430068969727]},"r":{"a":0,"k":0},"sa":{"a":0,"k":0},"o":{"a":0,"k":100}}]},{"ty":"gr","bm":0,"hd":false,"nm":"Group 2","it":[{"ty":"sh","bm":0,"hd":false,"nm":"Path 2","d":1,"ks":{"a":0,"k":{"c":true,"i":[[0,0],[0,46.68199999999999],[-46.68189999999999,0],[0,-46.6818],[46.68180000000001,0]],"o":[[-46.68189999999999,0],[0,-46.6818],[46.68180000000001,0],[0,46.68199999999999],[0,0]],"v":[[85.0272,169.55],[0.5,85.025],[85.0272,0.5],[169.554,85.025],[85.0272,169.55]]}}},{"ty":"st","bm":0,"hd":false,"nm":"Stroke","lc":1,"lj":1,"ml":4,"o":{"a":0,"k":0},"w":{"a":0,"k":1},"c":{"a":0,"k":[0.1098,0.3647,0.6]}},{"ty":"tr","a":{"a":0,"k":[85.0270004272461,85.0250015258789]},"s":{"a":0,"k":[100,100]},"sk":{"a":0,"k":0},"p":{"a":0,"k":[85.0270004272461,85.0250015258789]},"r":{"a":0,"k":0},"sa":{"a":0,"k":0},"o":{"a":0,"k":100}}]}],"ind":1},{"ty":4,"nm":"eye-base-2","sr":1,"st":0,"op":129.98,"ip":0,"hd":false,"ddd":0,"bm":0,"hasMask":false,"ao":0,"ks":{"a":{"a":0,"k":[250,250.00000000000023]},"s":{"a":0,"k":[29,29]},"sk":{"a":0,"k":0},"p":{"a":1,"k":[{"o":{"x":0.167,"y":0.167},"i":{"x":0.833,"y":0.833},"s":[638.9643,1401.5193],"t":0},{"o":{"x":0.167,"y":0.167},"i":{"x":0.833,"y":0.833},"s":[638.9643,1401.5193],"t":18},{"s":[1406.9643,1401.5193],"t":78}]},"r":{"a":0,"k":0},"sa":{"a":0,"k":0},"o":{"a":0,"k":100}},"shapes":[{"ty":"gr","bm":0,"hd":false,"nm":"Group 1","it":[{"ty":"rc","bm":0,"hd":false,"nm":"Rectangle 1","d":1,"p":{"a":0,"k":[190,250]},"r":{"a":0,"k":220},"s":{"a":0,"k":[440,440]}},{"ty":"st","bm":0,"hd":false,"nm":"Stroke","lc":1,"lj":1,"ml":4,"o":{"a":0,"k":100},"w":{"a":0,"k":60},"c":{"a":0,"k":[0.9804,0.9882,0.9961]}},{"ty":"tr","a":{"a":0,"k":[189.99999999999955,250]},"s":{"a":0,"k":[100,-100]},"sk":{"a":0,"k":0},"p":{"a":0,"k":[250.00000000000048,250.00000000000003]},"r":{"a":0,"k":180},"sa":{"a":0,"k":0},"o":{"a":0,"k":100}}]}],"ind":2},{"ty":4,"nm":"eye-sub-base-2","sr":1,"st":0,"op":129.98,"ip":0,"hd":false,"ddd":0,"bm":0,"hasMask":false,"ao":0,"ks":{"a":{"a":0,"k":[125,125]},"s":{"a":0,"k":[29,29]},"sk":{"a":0,"k":0},"p":{"a":1,"k":[{"o":{"x":0.167,"y":0.167},"i":{"x":0.833,"y":0.833},"s":[638.9643,1401.5193],"t":0},{"o":{"x":0.167,"y":0.167},"i":{"x":0.833,"y":0.833},"s":[638.9643,1401.5193],"t":18},{"s":[1406.9643,1401.5193],"t":78}]},"r":{"a":0,"k":0},"sa":{"a":0,"k":0},"o":{"a":0,"k":100}},"shapes":[{"ty":"gr","bm":0,"hd":false,"nm":"Group 1","it":[{"ty":"sh","bm":0,"hd":false,"nm":"Path 1","d":1,"ks":{"a":0,"k":{"c":true,"i":[[0,0],[0,56.60900000000001],[56.60900000000001,0],[0,-56.6092],[-56.6092,0]],"o":[[56.60900000000001,0],[0,-56.6092],[-56.6092,0],[0,56.60900000000001],[0,0]],"v":[[125,227.5],[227.5,125],[125,22.5],[22.5,125],[125,227.5]]}}},{"ty":"st","bm":0,"hd":false,"nm":"Stroke","lc":1,"lj":1,"ml":4,"o":{"a":0,"k":100},"w":{"a":0,"k":45},"c":{"a":0,"k":[0.9804,0.9882,0.9961]}},{"ty":"tr","a":{"a":0,"k":[0,0]},"s":{"a":0,"k":[100,100]},"sk":{"a":0,"k":0},"p":{"a":0,"k":[0,0]},"r":{"a":0,"k":0},"sa":{"a":0,"k":0},"o":{"a":0,"k":100}}]}],"ind":3},{"ty":4,"nm":"eye-base-1","sr":1,"st":0,"op":129.98,"ip":0,"hd":false,"ddd":0,"bm":0,"hasMask":false,"ao":0,"ks":{"a":{"a":0,"k":[250,250.00000000000023]},"s":{"a":0,"k":[29,29]},"sk":{"a":0,"k":0},"p":{"a":1,"k":[{"o":{"x":0.167,"y":0.167},"i":{"x":0.833,"y":0.833},"s":[507.4316,1401.5193],"t":0},{"o":{"x":0.167,"y":0.167},"i":{"x":0.833,"y":0.833},"s":[507.4316,1401.5193],"t":18},{"s":[1275.5123,1401.5193],"t":78}]},"r":{"a":0,"k":0},"sa":{"a":0,"k":0},"o":{"a":0,"k":100}},"shapes":[{"ty":"gr","bm":0,"hd":false,"nm":"Group 1","it":[{"ty":"rc","bm":0,"hd":false,"nm":"Rectangle 1","d":1,"p":{"a":0,"k":[190,250]},"r":{"a":0,"k":220},"s":{"a":0,"k":[440,440]}},{"ty":"st","bm":0,"hd":false,"nm":"Stroke","lc":1,"lj":1,"ml":4,"o":{"a":0,"k":100},"w":{"a":0,"k":60},"c":{"a":0,"k":[0.9804,0.9882,0.9961]}},{"ty":"tr","a":{"a":0,"k":[0,0]},"s":{"a":0,"k":[100,-100]},"sk":{"a":0,"k":0},"p":{"a":0,"k":[440,0]},"r":{"a":0,"k":180},"sa":{"a":0,"k":0},"o":{"a":0,"k":100}}]}],"ind":4},{"ty":4,"nm":"eye-sub-base-1","sr":1,"st":0,"op":129.98,"ip":0,"hd":false,"ddd":0,"bm":0,"hasMask":false,"ao":0,"ks":{"a":{"a":0,"k":[125,125]},"s":{"a":0,"k":[29,29]},"sk":{"a":0,"k":0},"p":{"a":1,"k":[{"o":{"x":0.167,"y":0.167},"i":{"x":0.833,"y":0.833},"s":[507.4316,1401.5193],"t":0},{"o":{"x":0.167,"y":0.167},"i":{"x":0.833,"y":0.833},"s":[507.4316,1401.5193],"t":18},{"s":[1275.5123,1401.5193],"t":78}]},"r":{"a":0,"k":0},"sa":{"a":0,"k":0},"o":{"a":0,"k":100}},"shapes":[{"ty":"gr","bm":0,"hd":false,"nm":"Group 1","it":[{"ty":"sh","bm":0,"hd":false,"nm":"Path 1","d":1,"ks":{"a":0,"k":{"c":true,"i":[[0,0],[0,56.60900000000001],[56.60900000000001,0],[0,-56.6092],[-56.6092,0]],"o":[[56.60900000000001,0],[0,-56.6092],[-56.6092,0],[0,56.60900000000001],[0,0]],"v":[[125,227.5],[227.5,125],[125,22.5],[22.5,125],[125,227.5]]}}},{"ty":"st","bm":0,"hd":false,"nm":"Stroke","lc":1,"lj":1,"ml":4,"o":{"a":0,"k":100},"w":{"a":0,"k":45},"c":{"a":0,"k":[0.9804,0.9882,0.9961]}},{"ty":"tr","a":{"a":0,"k":[0,0]},"s":{"a":0,"k":[100,100]},"sk":{"a":0,"k":0},"p":{"a":0,"k":[0,0]},"r":{"a":0,"k":0},"sa":{"a":0,"k":0},"o":{"a":0,"k":100}}]}],"ind":5},{"ty":4,"nm":"eye-center-1","sr":1,"st":0,"op":129.98,"ip":0,"hd":false,"ddd":0,"bm":0,"hasMask":false,"ao":0,"ks":{"a":{"a":0,"k":[85.23970013856888,85.27697747945786]},"s":{"a":0,"k":[29,29]},"sk":{"a":0,"k":0},"p":{"a":1,"k":[{"o":{"x":0.167,"y":0.167},"i":{"x":0.833,"y":0.833},"s":[507.4316,1401.5193],"t":0},{"o":{"x":0.167,"y":0.167},"i":{"x":0.833,"y":0.833},"s":[507.4316,1401.5193],"t":18},{"s":[1275.5123,1401.5193],"t":78}]},"r":{"a":1,"k":[{"o":{"x":0.167,"y":0.167},"i":{"x":0.833,"y":0.833},"s":[0],"t":0},{"o":{"x":0.167,"y":0.167},"i":{"x":0.833,"y":0.833},"s":[0],"t":18},{"s":[1080],"t":78}]},"sa":{"a":0,"k":0},"o":{"a":0,"k":100}},"shapes":[{"ty":"gr","bm":0,"hd":false,"nm":"Group 1","it":[{"ty":"sh","bm":0,"hd":false,"nm":"Path 1","d":1,"ks":{"a":0,"k":{"c":true,"i":[[0,0],[0,0],[0,0],[0,0],[0,0]],"o":[[0,0],[0,0],[0,0],[0,0],[0,0]],"v":[[123.919,33],[123.586,32.6272],[123.89,32.3558],[124.217,32.5982],[123.919,33]]}}},{"ty":"sh","bm":0,"hd":false,"nm":"Path 2","d":1,"ks":{"a":0,"k":{"c":true,"i":[[0,0],[0,0],[0,0],[0,0],[0,0]],"o":[[0,0],[0,0],[0,0],[0,0],[0,0]],"v":[[28.9998,117.852],[28.5678,118.104],[28.3624,117.751],[28.6666,117.479],[28.9998,117.852]]}}},{"ty":"sh","bm":0,"hd":false,"nm":"Path 3","d":1,"ks":{"a":0,"k":{"c":true,"i":[[0,0],[0,0],[0,0],[0,0],[0,0]],"o":[[0,0],[0,0],[0,0],[0,0],[0,0]],"v":[[124.925,136.691],[125.404,136.837],[125.357,136.99],[125.231,137.087],[124.925,136.691]]}}},{"ty":"sh","bm":0,"hd":false,"nm":"Path 4","d":1,"ks":{"a":0,"k":{"c":true,"i":[[0,0],[0,0],[0,0],[0,0],[0,0]],"o":[[0,0],[0,0],[0,0],[0,0],[0,0]],"v":[[146.925,64.6184],[147.399,64.4597],[147.45,64.6114],[147.403,64.7644],[146.925,64.6184]]}}},{"ty":"sh","bm":0,"hd":false,"nm":"Path 5","d":1,"ks":{"a":0,"k":{"c":true,"i":[[0,0],[0,0],[0,0],[0,0],[0,0]],"o":[[0,0],[0,0],[0,0],[0,0],[0,0]],"v":[[124.253,33.3728],[29.333,118.225],[28.6666,117.479],[123.586,32.6272],[124.253,33.3728]]}}},{"ty":"sh","bm":0,"hd":false,"nm":"Path 6","d":1,"ks":{"a":0,"k":{"c":true,"i":[[0,0],[-23.8149,0],[0,0],[11.352899999999998,19.48700000000001],[0,0]],"o":[[11.1812,19.193000000000012],[0,0],[-24.185200000000002,0],[0,0],[0,0]],"v":[[29.4318,117.6],[85.2397,149.7],[85.2397,150.7],[28.5678,118.104],[29.4318,117.6]]}}},{"ty":"sh","bm":0,"hd":false,"nm":"Path 7","d":1,"ks":{"a":0,"k":{"c":true,"i":[[0,0],[-10.89800000000001,8.403999999999996],[0,0],[15.052300000000002,0],[0,0]],"o":[[14.824299999999994,0],[0,0],[-11.066999999999993,8.535000000000025],[0,0],[0,0]],"v":[[85.2397,149.7],[124.62,136.296],[125.231,137.087],[85.2397,150.7],[85.2397,149.7]]}}},{"ty":"sh","bm":0,"hd":false,"nm":"Path 8","d":1,"ks":{"a":0,"k":{"c":true,"i":[[0,0],[0,0],[0,0],[0,0],[0,0]],"o":[[0,0],[0,0],[0,0],[0,0],[0,0]],"v":[[124.447,136.546],[146.447,64.4724],[147.403,64.7644],[125.404,136.837],[124.447,136.546]]}}},{"ty":"sh","bm":0,"hd":false,"nm":"Path 9","d":1,"ks":{"a":0,"k":{"c":true,"i":[[0,0],[10.522000000000006,7.795200000000001],[0,0],[-4.305000000000007,-12.861399999999996],[0,0]],"o":[[-4.239000000000004,-12.663300000000007],[0,0],[10.684000000000012,7.914900000000003],[0,0],[0,0]],"v":[[146.451,64.7771],[123.622,33.4018],[124.217,32.5982],[147.399,64.4597],[146.451,64.7771]]}}},{"ty":"fl","bm":0,"hd":false,"nm":"Fill","c":{"a":0,"k":[0.9804,0.9882,0.9961]},"r":1,"o":{"a":0,"k":100}},{"ty":"tr","a":{"a":0,"k":[0,0]},"s":{"a":0,"k":[100,100]},"sk":{"a":0,"k":0},"p":{"a":0,"k":[0,0]},"r":{"a":0,"k":0},"sa":{"a":0,"k":0},"o":{"a":0,"k":100}}]},{"ty":"gr","bm":0,"hd":false,"nm":"Group 2","it":[{"ty":"sh","bm":0,"hd":false,"nm":"Path 10","d":1,"ks":{"a":0,"k":{"c":true,"i":[[0,0],[0,0],[-24,0],[-10.982,8.469999999999999],[0,0],[10.604,7.854999999999997]],"o":[[0,0],[11.2671,19.340000000000003],[14.938299999999998,0],[0,0],[-4.27200000000002,-12.762399999999992],[0,0]],"v":[[123.919,33],[28.9998,117.852],[85.2397,150.2],[124.925,136.691],[146.925,64.6184],[123.919,33]]}}},{"ty":"fl","bm":0,"hd":false,"nm":"Fill","c":{"a":0,"k":[0.9804,0.9882,0.9961]},"r":2,"o":{"a":0,"k":100}},{"ty":"tr","a":{"a":0,"k":[0,0]},"s":{"a":0,"k":[100,100]},"sk":{"a":0,"k":0},"p":{"a":0,"k":[0,0]},"r":{"a":0,"k":0},"sa":{"a":0,"k":0},"o":{"a":0,"k":100}}]},{"ty":"gr","bm":0,"hd":false,"nm":"Group 3","it":[{"ty":"sh","bm":0,"hd":false,"nm":"Path 11","d":1,"ks":{"a":0,"k":{"c":true,"i":[[0,0],[0,46.682],[-46.6819,0],[0,-46.6819],[46.6814,0]],"o":[[-46.6819,0],[0,-46.6819],[46.6814,0],[0,46.682],[0,0]],"v":[[85.2396,169.802],[0.712402,85.277],[85.2396,0.751953],[169.767,85.277],[85.2396,169.802]]}}},{"ty":"st","bm":0,"hd":false,"nm":"Stroke","lc":1,"lj":1,"ml":4,"o":{"a":0,"k":100},"w":{"a":0,"k":0},"c":{"a":0,"k":[0.1098,0.3647,0.6]}},{"ty":"tr","a":{"a":0,"k":[0,0]},"s":{"a":0,"k":[100,100]},"sk":{"a":0,"k":0},"p":{"a":0,"k":[0,0]},"r":{"a":0,"k":0},"sa":{"a":0,"k":0},"o":{"a":0,"k":100}}]}],"ind":6},{"ty":4,"nm":"Path 9","sr":1,"st":0,"op":150,"ip":0,"hd":false,"ddd":0,"bm":0,"hasMask":false,"ao":0,"ks":{"a":{"a":0,"k":[744.9545288085938,317.1284484863281]},"s":{"a":1,"k":[{"o":{"x":0.167,"y":0.167},"i":{"x":0.833,"y":0.833},"s":[100,100],"t":0},{"o":{"x":0.167,"y":0.167},"i":{"x":0.833,"y":0.833},"s":[100,100],"t":18},{"o":{"x":0.167,"y":0.167},"i":{"x":0.833,"y":0.833},"s":[88,100],"t":25},{"o":{"x":0.167,"y":0.167},"i":{"x":0.833,"y":0.833},"s":[79.6667,69.16666666666666],"t":31},{"o":{"x":0.167,"y":0.167},"i":{"x":0.833,"y":0.833},"s":[37,29],"t":35},{"s":[0,0],"t":36}]},"sk":{"a":0,"k":0},"p":{"a":1,"k":[{"o":{"x":0.167,"y":0.167},"i":{"x":0.833,"y":0.833},"s":[737.8117,1399.9768],"t":0},{"o":{"x":0.167,"y":0.167},"i":{"x":0.833,"y":0.833},"s":[737.8117,1399.9768],"t":18},{"o":{"x":0.167,"y":0.167},"i":{"x":0.833,"y":0.833},"s":[820.8117,1395.5652],"t":25},{"o":{"x":0.167,"y":0.167},"i":{"x":0.833,"y":0.833},"s":[892.9545,1382.1284],"t":31},{"o":{"x":0.167,"y":0.167},"i":{"x":0.833,"y":0.833},"s":[912.7323,1364.0728],"t":35},{"s":[816.9545,1417.1284],"t":48}]},"r":{"a":1,"k":[{"o":{"x":0.167,"y":0.167},"i":{"x":0.833,"y":0.833},"s":[0],"t":0},{"o":{"x":0.167,"y":0.167},"i":{"x":0.833,"y":0.833},"s":[0],"t":18},{"o":{"x":0.167,"y":0.167},"i":{"x":0.833,"y":0.833},"s":[1],"t":25},{"o":{"x":0.167,"y":0.167},"i":{"x":0.833,"y":0.833},"s":[0],"t":31},{"s":[15],"t":35}]},"sa":{"a":0,"k":0},"o":{"a":1,"k":[{"o":{"x":0.167,"y":0.167},"i":{"x":0.833,"y":0.833},"s":[100],"t":0},{"o":{"x":0.167,"y":0.167},"i":{"x":0.833,"y":0.833},"s":[100],"t":18},{"o":{"x":0.167,"y":0.167},"i":{"x":0.833,"y":0.833},"s":[100],"t":25},{"o":{"x":0.167,"y":0.167},"i":{"x":0.833,"y":0.833},"s":[100],"t":31},{"o":{"x":0.167,"y":0.167},"i":{"x":0.833,"y":0.833},"s":[100],"t":35},{"s":[0],"t":36}]}},"shapes":[{"ty":"sh","bm":0,"hd":false,"nm":"PATH Shape Path 9","d":1,"ks":{"a":0,"k":{"c":true,"i":[[31.74339897476625,30.648158154981502],[0,0],[-17.818592252116787,-9.443447273371419],[0,0],[0,0]],"o":[[-0.15825597167395244,-0.1582559716740093],[0,0],[17.818592252116787,9.443447273371419],[0,0],[0,0]],"v":[[705.7639096619281,330.25657036255774],[708.9316661083164,282.0357986276664],[736.2524165308282,323.1291322769359],[765.3498835933439,325.8106813945473],[765.5063381596165,350.1300991824778]]}}},{"ty":"fl","bm":0,"hd":false,"nm":"Fill","c":{"a":0,"k":[0.9804,0.9882,0.9961]},"r":2,"o":{"a":0,"k":100}},{"ty":"st","bm":0,"hd":false,"nm":"Stroke","lc":2,"lj":2,"ml":1,"o":{"a":0,"k":0},"w":{"a":0,"k":0},"c":{"a":0,"k":[0,0,0]}}],"ind":7},{"ty":4,"nm":"Rectangle 2","sr":1,"st":0,"op":150,"ip":0,"hd":false,"ddd":0,"bm":0,"hasMask":false,"ao":0,"ks":{"a":{"a":0,"k":[0,0]},"s":{"a":1,"k":[{"o":{"x":0.167,"y":0.167},"i":{"x":0.833,"y":0.833},"s":[53.2687981195979,48.256676264324874],"t":31},{"o":{"x":0.167,"y":0.167},"i":{"x":0.833,"y":0.833},"s":[803.7183522573814,48.256676264324874],"t":35},{"o":{"x":0.167,"y":0.167},"i":{"x":0.833,"y":0.833},"s":[2263.600615966161,48.25667626432488],"t":48},{"o":{"x":0.167,"y":0.167},"i":{"x":0.833,"y":0.833},"s":[5912.049445109224,48.256676264324874],"t":78},{"o":{"x":0.167,"y":0.167},"i":{"x":0.833,"y":0.833},"s":[5912.049445109224,48.256676264324874],"t":81},{"s":[5912.049445109224,8119.009414944834],"t":90}]},"sk":{"a":0,"k":0},"p":{"a":1,"k":[{"o":{"x":0.167,"y":0.167},"i":{"x":0.833,"y":0.833},"s":[792.3546,1465.3117],"t":31},{"o":{"x":0.167,"y":0.167},"i":{"x":0.833,"y":0.833},"s":[769.3546,1465.3117],"t":35},{"o":{"x":0.167,"y":0.167},"i":{"x":0.833,"y":0.833},"s":[789.5146,1465.3117],"t":48},{"o":{"x":0.167,"y":0.167},"i":{"x":0.833,"y":0.833},"s":[796.0746,1465.3117],"t":70},{"o":{"x":0.167,"y":0.167},"i":{"x":0.833,"y":0.833},"s":[601.3546,1465.3117],"t":78},{"s":[601.3546,1465.3117],"t":81}]},"r":{"a":0,"k":0},"sa":{"a":0,"k":0},"o":{"a":1,"k":[{"o":{"x":0.167,"y":0.167},"i":{"x":0.833,"y":0.833},"s":[0],"t":30},{"s":[100],"t":31}]}},"shapes":[{"ty":"rc","bm":0,"hd":false,"nm":"Rectangle Path 2","d":1,"p":{"a":0,"k":[0,0]},"r":{"a":0,"k":0},"s":{"a":0,"k":[20.370176174496578,36.34778733221481]}},{"ty":"fl","bm":0,"hd":false,"nm":"Fill","c":{"a":0,"k":[1,1,1]},"r":2,"o":{"a":0,"k":100}}],"ind":8}],"v":"5.7.0","fr":30,"op":129.98,"ip":0,"assets":[]}